[
    {
      "id": 1,
      "question": "A line organization is characterized by a direct chain of command from the top level to the bottom, with each employee reporting to only one ________.",
      "options": [
        "boss",
        "manager",
        "supervisor",
        "leader"
      ],
      "answer": 1
    },
    {
      "id": 2,
      "question": "In a functional organization, the company is divided into departments based on ________.",
      "options": [
        "roles",
        "functions",
        "specialties",
        "geographies"
      ],
      "answer": 2
    },
    {
      "id": 3,
      "question": "A line and staff organization combines line managers who handle decision-making with staff experts who provide ________.",
      "options": [
        "advice",
        "orders",
        "decisions",
        "strategies"
      ],
      "answer": 1
    },
    {
      "id": 4,
      "question": "Project organization is a temporary structure created for a specific ________.",
      "options": [
        "project",
        "goal",
        "objective",
        "mission"
      ],
      "answer": 1
    },
    {
      "id": 5,
      "question": "In a matrix organization, employees report to both a functional manager and a ________.",
      "options": [
        "project manager",
        "department head",
        "team leader",
        "division manager"
      ],
      "answer": 1
    },
    {
      "id": 6,
      "question": "The first step in organizing is to define what the organization wants to achieve by setting clear ________.",
      "options": [
        "objectives",
        "goals",
        "targets",
        "missions"
      ],
      "answer": 1
    },
    {
      "id": 7,
      "question": "The next step in organizing is to list all necessary activities and group similar tasks into ________.",
      "options": [
        "departments",
        "teams",
        "projects",
        "divisions"
      ],
      "answer": 1
    },
    {
      "id": 8,
      "question": "Organizing involves assigning tasks to different individuals or ________.",
      "options": [
        "departments",
        "teams",
        "projects",
        "divisions"
      ],
      "answer": 1
    },
    {
      "id": 9,
      "question": "The organization defines who will report to whom by establishing a clear ________.",
      "options": [
        "hierarchy",
        "structure",
        "framework",
        "system"
      ],
      "answer": 1
    },
    {
      "id": 10,
      "question": "Organizing ensures that different departments work together ________.",
      "options": [
        "smoothly",
        "efficiently",
        "effectively",
        "productively"
      ],
      "answer": 1
    },
    {
      "id": 11,
      "question": "The organization must check its performance regularly and make improvements if needed through ________.",
      "options": [
        "review and improvement",
        "evaluation and adjustment",
        "analysis and correction",
        "assessment and modification"
      ],
      "answer": 1
    },
    {
      "id": 12,
      "question": "A line organization is characterized by a direct chain of command from the top level to the bottom, with each employee reporting to only one ________.",
      "options": [
        "boss",
        "manager",
        "supervisor",
        "leader"
      ],
      "answer": 1
    },
    {
      "id": 13,
      "question": "In a functional organization, the company is divided into departments based on ________.",
      "options": [
        "roles",
        "functions",
        "specialties",
        "geographies"
      ],
      "answer": 2
    },
    {
      "id": 14,
      "question": "A line and staff organization combines line managers who handle decision-making with staff experts who provide ________.",
      "options": [
        "advice",
        "orders",
        "decisions",
        "strategies"
      ],
      "answer": 1
    },
    {
      "id": 15,
      "question": "Project organization is a temporary structure created for a specific ________.",
      "options": [
        "project",
        "goal",
        "objective",
        "mission"
      ],
      "answer": 1
    },
    {
      "id": 16,
      "question": "In a matrix organization, employees report to both a functional manager and a ________.",
      "options": [
        "project manager",
        "department head",
        "team leader",
        "division manager"
      ],
      "answer": 1
    },
    {
      "id": 17,
      "question": "The first step in organizing is to define what the organization wants to achieve by setting clear ________.",
      "options": [
        "objectives",
        "goals",
        "targets",
        "missions"
      ],
      "answer": 1
    },
    {
      "id": 18,
      "question": "The next step in organizing is to list all necessary activities and group similar tasks into ________.",
      "options": [
        "departments",
        "teams",
        "projects",
        "divisions"
      ],
      "answer": 1
    },
    {
      "id": 19,
      "question": "Organizing involves assigning tasks to different individuals or ________.",
      "options": [
        "departments",
        "teams",
        "projects",
        "divisions"
      ],
      "answer": 1
    },
    {
      "id": 20,
      "question": "The organization defines who will report to whom by establishing a clear ________.",
      "options": [
        "hierarchy",
        "structure",
        "framework",
        "system"
      ],
      "answer": 1
    },
    {
      "id": 21,
      "question": "Organizing ensures that different departments work together ________.",
      "options": [
        "smoothly",
        "efficiently",
        "effectively",
        "productively"
      ],
      "answer": 1
    },
    {
      "id": 22,
      "question": "The organization must check its performance regularly and make improvements if needed through ________.",
      "options": [
        "review and improvement",
        "evaluation and adjustment",
        "analysis and correction",
        "assessment and modification"
      ],
      "answer": 1
    },
    {
      "id": 23,
      "question": "A line organization is characterized by a direct chain of command from the top level to the bottom, with each employee reporting to only one ________.",
      "options": [
        "boss",
        "manager",
        "supervisor",
        "leader"
      ],
      "answer": 1
    },
    {
      "id": 24,
      "question": "In a functional organization, the company is divided into departments based on ________.",
      "options": [
        "roles",
        "functions",
        "specialties",
        "geographies"
      ],
      "answer": 2
    },
    {
      "id": 25,
      "question": "A line and staff organization combines line managers who handle decision-making with staff experts who provide ________.",
      "options": [
        "advice",
        "orders",
        "decisions",
        "strategies"
      ],
      "answer": 1
    },
    {
      "id": 26,
      "question": "Project organization is a temporary structure created for a specific ________.",
      "options": [
        "project",
        "goal",
        "objective",
        "mission"
      ],
      "answer": 1
    },
    {
      "id": 27,
      "question": "In a matrix organization, employees report to both a functional manager and a ________.",
      "options": [
        "project manager",
        "department head",
        "team leader",
        "division manager"
      ],
      "answer": 1
    },
    {
      "id": 28,
      "question": "The first step in organizing is to define what the organization wants to achieve by setting clear ________.",
      "options": [
        "objectives",
        "goals",
        "targets",
        "missions"
      ],
      "answer": 1
    },
    {
      "id": 29,
      "question": "The next step in organizing is to list all necessary activities and group similar tasks into ________.",
      "options": [
        "departments",
        "teams",
        "projects",
        "divisions"
      ],
      "answer": 1
    },
    {
      "id": 30,
      "question": "Organizing involves assigning tasks to different individuals or ________.",
      "options": [
        "departments",
        "teams",
        "projects",
        "divisions"
      ],
      "answer": 1
    },
    {
      "id": 31,
      "question": "The organization defines who will report to whom by establishing a clear ________.",
      "options": [
        "hierarchy",
        "structure",
        "framework",
        "system"
      ],
      "answer": 1
    },
    {
      "id": 32,
      "question": "Organizing ensures that different departments work together ________.",
      "options": [
        "smoothly",
        "efficiently",
        "effectively",
        "productively"
      ],
      "answer": 1
    },
    {
      "id": 33,
      "question": "The organization must check its performance regularly and make improvements if needed through ________.",
      "options": [
        "review and improvement",
        "evaluation and adjustment",
        "analysis and correction",
        "assessment and modification"
      ],
      "answer": 1
    },
    {
      "id": 34,
      "question": "A line organization is characterized by a direct chain of command from the top level to the bottom, with each employee reporting to only one ________.",
      "options": [
        "boss",
        "manager",
        "supervisor",
        "leader"
      ],
      "answer": 1
    },
    {
      "id": 35,
      "question": "In a functional organization, the company is divided into departments based on ________.",
      "options": [
        "roles",
        "functions",
        "specialties",
        "geographies"
      ],
      "answer": 2
    },
    {
      "id": 36,
      "question": "A line and staff organization combines line managers who handle decision-making with staff experts who provide ________.",
      "options": [
        "advice",
        "orders",
        "decisions",
        "strategies"
      ],
      "answer": 1
    },
    {
      "id": 37,
      "question": "Project organization is a temporary structure created for a specific ________.",
      "options": [
        "project",
        "goal",
        "objective",
        "mission"
      ],
      "answer": 1
    },
    {
      "id": 38,
      "question": "In a matrix organization, employees report to both a functional manager and a ________.",
      "options": [
        "project manager",
        "department head",
        "team leader",
        "division manager"
      ],
      "answer": 1
    },
    {
      "id": 39,
      "question": "The first step in organizing is to define what the organization wants to achieve by setting clear ________.",
      "options": [
        "objectives",
        "goals",
        "targets",
        "missions"
      ],
      "answer": 1
    },
    {
      "id": 40,
      "question": "The next step in organizing is to list all necessary activities and group similar tasks into ________.",
      "options": [
        "departments",
        "teams",
        "projects",
        "divisions"
      ],
      "answer": 1
    },
    {
      "id": 41,
      "question": "Organizing involves assigning tasks to different individuals or ________.",
      "options": [
        "departments",
        "teams",
        "projects",
        "divisions"
      ],
      "answer": 1
    },
    {
      "id": 42,
      "question": "The organization defines who will report to whom by establishing a clear ________.",
      "options": [
        "hierarchy",
        "structure",
        "framework",
        "system"
      ],
      "answer": 1
    },
    {
      "id": 43,
      "question": "Organizing ensures that different departments work together ________.",
      "options": [
        "smoothly",
        "efficiently",
        "effectively",
        "productively"
      ],
      "answer": 1
    },
    {
      "id": 44,
      "question": "The organization must check its performance regularly and make improvements if needed through ________.",
      "options": [
        "review and improvement",
        "evaluation and adjustment",
        "analysis and correction",
        "assessment and modification"
      ],
      "answer": 1
    },
    {
      "id": 45,
      "question": "A line organization is characterized by a direct chain of command from the top level to the bottom, with each employee reporting to only one ________.",
      "options": [
        "boss",
        "manager",
        "supervisor",
        "leader"
      ],
      "answer": 1
    },
    {
      "id": 46,
      "question": "In a functional organization, the company is divided into departments based on ________.",
      "options": [
        "roles",
        "functions",
        "specialties",
        "geographies"
      ],
      "answer": 2
    },
    {
      "id": 47,
      "question": "A line and staff organization combines line managers who handle decision-making with staff experts who provide ________.",
      "options": [
        "advice",
        "orders",
        "decisions",
        "strategies"
      ],
      "answer": 1
    },
    {
      "id": 48,
      "question": "Project organization is a temporary structure created for a specific ________.",
      "options": [
        "project",
        "goal",
        "objective",
        "mission"
      ],
      "answer": 1
    },
    {
      "id": 49,
      "question": "In a matrix organization, employees report to both a functional manager and a ________.",
      "options": [
        "project manager",
        "department head",
        "team leader",
        "division manager"
      ],
      "answer": 1
    },
    {
      "id": 50,
      "question": "The first step in organizing is to define what the organization wants to achieve by setting clear ________.",
      "options": [
        "objectives",
        "goals",
        "targets",
        "missions"
      ],
      "answer": 1
    }
]
  